python_trueconf_bot-1.1.2.dist-info/licenses/LICENSE
trueconf/__init__.py
trueconf/_version.py
trueconf/exceptions.py
trueconf/loggers.py
trueconf/py.typed
trueconf/client/__init__.py
trueconf/client/bot.py
trueconf/client/context_controller.py
trueconf/client/session.py
trueconf/dispatcher/__init__.py
trueconf/dispatcher/dispatcher.py
trueconf/dispatcher/router.py
trueconf/enums/__init__.py
trueconf/enums/aouth_error.py
trueconf/enums/chat_participant_role.py
trueconf/enums/chat_type.py
trueconf/enums/envelope_author_type.py
trueconf/enums/file_ready_state.py
trueconf/enums/incoming_update_method.py
trueconf/enums/message_type.py
trueconf/enums/parse_mode.py
trueconf/enums/survey_type.py
trueconf/enums/update_type.py
trueconf/filters/__init__.py
trueconf/filters/base.py
trueconf/filters/command.py
trueconf/filters/instance_of.py
trueconf/filters/message.py
trueconf/filters/method.py
trueconf/methods/__init__.py
trueconf/methods/add_participant_to_chat.py
trueconf/methods/auth.py
trueconf/methods/base.py
trueconf/methods/change_participant_role.py
trueconf/methods/create_channel.py
trueconf/methods/create_favorites_chat.py
trueconf/methods/create_group_chat.py
trueconf/methods/create_p2p_chat.py
trueconf/methods/edit_message.py
trueconf/methods/edit_survey.py
trueconf/methods/forward_message.py
trueconf/methods/get_chat_by_id.py
trueconf/methods/get_chat_history.py
trueconf/methods/get_chat_participants.py
trueconf/methods/get_chats.py
trueconf/methods/get_file_info.py
trueconf/methods/get_message_by_id.py
trueconf/methods/get_user_display_name.py
trueconf/methods/has_chat_participant.py
trueconf/methods/remove_chat.py
trueconf/methods/remove_message.py
trueconf/methods/remove_participant_from_chat.py
trueconf/methods/send_file.py
trueconf/methods/send_message.py
trueconf/methods/send_survey.py
trueconf/methods/subscribe_file_progress.py
trueconf/methods/unsubscribe_file_progress.py
trueconf/methods/upload_file.py
trueconf/types/__init__.py
trueconf/types/author_box.py
trueconf/types/chat_participant.py
python_trueconf_bot-1.1.2.dist-info/METADATA
python_trueconf_bot-1.1.2.dist-info/WHEEL
python_trueconf_bot-1.1.2.dist-info/top_level.txt
python_trueconf_bot-1.1.2.dist-info/RECORD
