Metadata-Version: 2.4
Name: python-trueconf-bot
Version: 1.1.2
Summary: Lightweight and powerful framework for the TrueConf Server Chatbot API
Author-email: TrueConf LLC <info@trueconf.com>, Anton Baadzhi <baadzhianton@gmail.com>
License-Expression: BSD-3-Clause-Clear
Project-URL: Homepage, https://github.com/TrueConf/python-trueconf-bot
Project-URL: Repository, https://github.com/TrueConf/python-trueconf-bot
Project-URL: Documentation, https://trueconf.github.io/python-trueconf-bot
Project-URL: Issues, https://github.com/TrueConf/python-trueconf-bot/issues
Keywords: trueconf,chatbot,bot,api,framework,wrapper,asyncio,websocket
Classifier: Development Status :: 5 - Production/Stable
Classifier: Environment :: Console
Classifier: Framework :: AsyncIO
Classifier: Typing :: Typed
Classifier: Intended Audience :: Developers
Classifier: Programming Language :: Python :: 3.10
Classifier: Programming Language :: Python :: 3.11
Classifier: Programming Language :: Python :: 3.12
Classifier: Programming Language :: Python :: 3.13
Classifier: Topic :: Software Development :: Libraries :: Python Modules
Classifier: Topic :: Communications :: Chat
Requires-Python: >=3.10
License-File: LICENSE
Requires-Dist: websockets
Requires-Dist: httpx
Requires-Dist: mashumaro
Requires-Dist: aiofiles
Requires-Dist: magic-filter
Requires-Dist: aiohttp
Requires-Dist: async-property
Requires-Dist: typing_extensions>=4.15.0
Provides-Extra: python-magic
Requires-Dist: python-magic>=0.4.27; extra == "python-magic"
Dynamic: license-file
